webhook_tunnel/__init__.py
webhook_tunnel/cli.py
webhook_tunnel/manager.py
webhook_tunnel/proxy.py
webhook_tunnel/tui.py
webhook_tunnel/webhook_server.py
webhook_mannager-1.0.1.dist-info/LICENSE
webhook_mannager-1.0.1.dist-info/METADATA
webhook_mannager-1.0.1.dist-info/WHEEL
webhook_mannager-1.0.1.dist-info/entry_points.txt
webhook_mannager-1.0.1.dist-info/top_level.txt
webhook_mannager-1.0.1.dist-info/RECORD
