Metadata-Version: 2.1
Name: webhook-mannager
Version: 1.0.1
Summary: Expose local ports with custom DNS for webhook testing - TUI interface
Home-page: https://github.com/w4lto/webhook-manager
Author: Joao Pedro Albergaria de Castro
Author-email: Joao Pedro Albergaria de Castro <jpbrasil373@gmail.com>
License: MIT
Project-URL: Homepage, https://github.com/w4lto/webhook-manager
Project-URL: Documentation, https://github.com/w4lto/webhook-manager/blob/main/README.md
Project-URL: Repository, https://github.com/w4lto/webhook-manager
Project-URL: Bug Tracker, https://github.com/w4lto/webhook-manager/issues
Keywords: webhook,tunnel,ngrok,localhost,development,testing,port-forwarding,dns,tui
Classifier: Development Status :: 4 - Beta
Classifier: Intended Audience :: Developers
Classifier: Topic :: Software Development :: Testing
Classifier: Topic :: Internet :: WWW/HTTP
Classifier: License :: OSI Approved :: MIT License
Classifier: Programming Language :: Python :: 3
Classifier: Programming Language :: Python :: 3.8
Classifier: Programming Language :: Python :: 3.9
Classifier: Programming Language :: Python :: 3.10
Classifier: Programming Language :: Python :: 3.11
Classifier: Programming Language :: Python :: 3.12
Classifier: Operating System :: OS Independent
Classifier: Environment :: Console
Requires-Python: >=3.8
License-File: LICENSE
Requires-Dist: click>=8.1.0
Requires-Dist: textual>=0.47.0
Requires-Dist: rich>=13.0.0
Requires-Dist: psutil>=5.9.0
Provides-Extra: dev
Requires-Dist: pytest>=7.0.0; extra == "dev"
Requires-Dist: pytest-asyncio>=0.21.0; extra == "dev"
Requires-Dist: black>=23.0.0; extra == "dev"
Requires-Dist: flake8>=6.0.0; extra == "dev"
Requires-Dist: mypy>=1.0.0; extra == "dev"
Provides-Extra: webhook-server
Requires-Dist: flask>=3.0.0; extra == "webhook-server"
